protocol_parser/MarkdownParser.py
protocol_parser/ParserBase.py
protocol_parser/__init__.py
protocol_parser/cli.py
ctn_protocolparser-0.1.1.dist-info/entry_points.txt
ctn_protocolparser-0.1.1.dist-info/LICENSE
ctn_protocolparser-0.1.1.dist-info/WHEEL
ctn_protocolparser-0.1.1.dist-info/METADATA
ctn_protocolparser-0.1.1.dist-info/RECORD
